trio_util/__init__.py
trio_util/_async_bool.py
trio_util/_async_itertools.py
trio_util/_async_value.py
trio_util/_awaitables.py
trio_util/_cancel_scopes.py
trio_util/_compose_values.py
trio_util/_exceptions.py
trio_util/_iterators.py
trio_util/_periodic.py
trio_util/_ref_counted_default_dict.py
trio_util/_repeated_event.py
trio_util/_task_stats.py
trio_util/_trio_async_generator.py
trio_util/_version.py
trio_util-0.8.0.dist-info/LICENSE
trio_util-0.8.0.dist-info/METADATA
trio_util-0.8.0.dist-info/WHEEL
trio_util-0.8.0.dist-info/top_level.txt
trio_util-0.8.0.dist-info/RECORD
