Metadata-Version: 2.1
Name: trio_util
Version: 0.8.0
Summary: Utility library for the Trio async/await framework
Home-page: https://github.com/groove-x/trio-util
Author: GROOVE X, Inc.
Author-email: gx-sw@groove-x.com
License: MIT
Classifier: Development Status :: 3 - Alpha
Classifier: Intended Audience :: Developers
Classifier: License :: OSI Approved :: MIT License
Classifier: Programming Language :: Python :: 3 :: Only
Classifier: Programming Language :: Python :: 3.8
Classifier: Programming Language :: Python :: 3.9
Classifier: Programming Language :: Python :: 3.10
Classifier: Programming Language :: Python :: 3.11
Classifier: Programming Language :: Python :: 3.12
Classifier: Programming Language :: Python :: 3.13
Classifier: Framework :: Trio
Requires-Python: >=3.8
License-File: LICENSE
Requires-Dist: async-generator
Requires-Dist: trio >=0.11.0
